setup.py
actupac/Extrapolation.py
actupac/General.py
actupac/Interpolation.py
actupac/__init__.py
actupac.egg-info/PKG-INFO
actupac.egg-info/SOURCES.txt
actupac.egg-info/dependency_links.txt
actupac.egg-info/not-zip-safe
actupac.egg-info/top_level.txt