Metadata-Version: 1.0
Name: actupac
Version: 0.1
Summary: Interpolate and extrapolate interest rates
Home-page: UNKNOWN
Author: Jingde Guo
Author-email: guojingde17@163.com
License: UNKNOWN
Platform: UNKNOWN
